roboComponents/__init__.py
roboComponents/camera.py
roboComponents/distanceSensor.py
roboComponents/servo.py
roboLibs/__init__.py
roboLibs/sentenceMaker.py
robotyze_my_pi-0.6.dist-info/DESCRIPTION.rst
robotyze_my_pi-0.6.dist-info/METADATA
robotyze_my_pi-0.6.dist-info/RECORD
robotyze_my_pi-0.6.dist-info/WHEEL
robotyze_my_pi-0.6.dist-info/metadata.json
robotyze_my_pi-0.6.dist-info/top_level.txt
