Metadata-Version: 2.0
Name: robotyze-my-pi
Version: 0.6
Summary: Some packages to make coding on a Raspberry Pi much easier!
Home-page: http://github.com/robotyze/public
Author: Craig Wilkinson, Ummay Habiba
Author-email: info@robotyze.org
License: MIT
Platform: UNKNOWN
